cifcleaner/__init__.py
cifcleaner/filter/__init__.py
cifcleaner/filter/excel.py
cifcleaner/filter/format.py
cifcleaner/filter/info.py
cifcleaner/filter/min_distance.py
cifcleaner/filter/occupancy.py
cifcleaner/filter/supercell_size.py
cifcleaner/filter/tags.py
cifcleaner/preprocess/__init__.py
cifcleaner/preprocess/cif_editor.py
cifcleaner/preprocess/cif_parser.py
cifcleaner/preprocess/cif_parser_handler.py
cifcleaner/preprocess/supercell.py
cifcleaner/preprocess/supercell_handler.py
cifcleaner/util/__init__.py
cifcleaner/util/folder.py
cifcleaner/util/string_parser.py
cifcleaner/util/unit.py
preprocess/__init__.py
preprocess/cif_editor.py
preprocess/cif_parser.py
preprocess/cif_parser_handler.py
preprocess/supercell.py
preprocess/supercell_handler.py
util/__init__.py
util/folder.py
util/string_parser.py
util/unit.py
cifcleaner-0.25.dist-info/METADATA
cifcleaner-0.25.dist-info/WHEEL
cifcleaner-0.25.dist-info/top_level.txt
cifcleaner-0.25.dist-info/RECORD
